<?xml version="1.0" encoding="UTF-8"?><record_update>
    <sys_choice action="DELETE" field="u_request_type" table="x_58872_needit_needit" version="3">
        <sys_choice_set action="DELETE">
            <element>u_request_type</element>
            <name>x_58872_needit_needit</name>
            <sys_class_name>sys_choice_set</sys_class_name>
            <sys_created_by/>
            <sys_created_on/>
            <sys_id/>
            <sys_mod_count/>
            <sys_name/>
            <sys_package/>
            <sys_policy/>
            <sys_scope/>
            <sys_update_name/>
            <sys_updated_by/>
            <sys_updated_on>2020-09-24 23:10:16</sys_updated_on>
        </sys_choice_set>
    </sys_choice>
    <sys_update_version action="INSERT_OR_UPDATE">
        <action>DELETE</action>
        <application/>
        <file_path/>
        <instance_id>dd9971addbc1b7c0b847ac44d4961947</instance_id>
        <instance_name>dev83648</instance_name>
        <name>sys_choice_x_58872_needit_needit_u_request_type</name>
        <payload><![CDATA[<?xml version="1.0" encoding="UTF-8"?><record_update><sys_choice action="DELETE" field="u_request_type" table="x_58872_needit_needit" version="3"><sys_choice_set action="DELETE"><element>u_request_type</element><name>x_58872_needit_needit</name><sys_class_name>sys_choice_set</sys_class_name><sys_created_by/><sys_created_on/><sys_id/><sys_mod_count/><sys_name/><sys_package/><sys_policy/><sys_scope/><sys_update_name/><sys_updated_by/><sys_updated_on>2020-09-24 23:10:16</sys_updated_on></sys_choice_set></sys_choice></record_update>]]></payload>
        <payload_hash>1673447142</payload_hash>
        <record_name>NeedIt.Request type</record_name>
        <reverted_from/>
        <source>5066cb64db9710109e15cd3f299619d9</source>
        <source_table>sys_update_set</source_table>
        <state>previous</state>
        <sys_created_by>admin</sys_created_by>
        <sys_created_on>2020-09-24 23:10:16</sys_created_on>
        <sys_id>68806740db2310109e15cd3f299619b8</sys_id>
        <sys_mod_count>0</sys_mod_count>
        <sys_recorded_at>174c261b14b0000001</sys_recorded_at>
        <sys_updated_by>admin</sys_updated_by>
        <sys_updated_on>2020-09-24 23:10:16</sys_updated_on>
        <type>Choice list</type>
        <update_guid>e0806740d6231010b3b0b4aa5d60d2b8</update_guid>
        <update_guid_history>e0806740d6231010b3b0b4aa5d60d2b8:1673447142,ac806740fd2310108819465013c84eb4:-1701966180,e880674007231010bceb2fd46769e9b1:736548692,28806740642310103d092cc81a3674ae:833312879,e85f63e0051b1010d957815a58d1fa53:0,4c5f23e04d1b101033d400d8d6812343:-829300445,0c5f23e0b51b101011b500cb0fc7b53f:-1701966180,085f23e07f1b1010f481bdb77b24343c:736548692,045f23e00c1b10107366a611509eb439:833312879,18f65fa01dd71010ed54c158ee8d2334:0,7ee6dba0f5d71010eb21641bde5e274a:1673447142,36e6dba0d3d7101094ccd3fc3e589c47:-103233526,32e6dba094d71010e3c5628de42fe044:-854501905,fae6dba05ed71010c86e2c7f4537c640:878753447,baaf8f6ce6971010a20c9e1cf4be08c9:411213506</update_guid_history>
    </sys_update_version>
    <sys_metadata_delete action="INSERT_OR_UPDATE">
        <sys_audit_delete/>
        <sys_class_name>sys_metadata_delete</sys_class_name>
        <sys_created_by>admin</sys_created_by>
        <sys_created_on>2020-09-24 23:10:22</sys_created_on>
        <sys_db_object display_value="" name="sys_choice_set">sys_choice_set</sys_db_object>
        <sys_id>7d80a740db2310109e15cd3f299619e0</sys_id>
        <sys_metadata>7d80a740db2310109e15cd3f299619e0</sys_metadata>
        <sys_mod_count>0</sys_mod_count>
        <sys_name>u_request_type</sys_name>
        <sys_package display_value="NeedIt" source="x_58872_needit">6ead8e780f603200cd674f8ce1050ed1</sys_package>
        <sys_parent/>
        <sys_policy/>
        <sys_scope display_value="NeedIt">6ead8e780f603200cd674f8ce1050ed1</sys_scope>
        <sys_scope_delete display_value="">94872a8897db403e8ee69a431de2fca4</sys_scope_delete>
        <sys_update_name>sys_choice_x_58872_needit_needit_u_request_type</sys_update_name>
        <sys_update_version display_value="sys_choice_x_58872_needit_needit_u_request_type">68806740db2310109e15cd3f299619b8</sys_update_version>
        <sys_updated_by>admin</sys_updated_by>
        <sys_updated_on>2020-09-24 23:10:22</sys_updated_on>
    </sys_metadata_delete>
</record_update>
